spark_logs/__init__.py
spark_logs/dataproc.py
spark_logs/cli/__main__.py
spark_logs-0.0.2.dist-info/METADATA
spark_logs-0.0.2.dist-info/WHEEL
spark_logs-0.0.2.dist-info/entry_points.txt
spark_logs-0.0.2.dist-info/RECORD
