Metadata-Version: 2.4
Name: spark-logs
Version: 0.0.2
Summary: Download and optimize spark clusters automatically
Project-URL: Homepage, https://github.com/probably-nothing-labs/spark-logs
Project-URL: Bug Tracker, https://github.com/probably-nothing-labs/spark-logs/issues
Author-email: Matt Green <matt@denormalized.io>
License: MIT
Classifier: License :: OSI Approved :: MIT License
Classifier: Programming Language :: Python :: 3.12
Classifier: Topic :: Software Development :: Libraries :: Python Modules
Requires-Python: >=3.12
Requires-Dist: google-cloud-dataproc>=5.18.1
Requires-Dist: google-cloud-resource-manager>=1.14.2
Requires-Dist: google-cloud-storage>=3.1.0
Requires-Dist: google-cloud>=0.34.0
Requires-Dist: inquirer>=3.1.3
